Metadata-Version: 1.0
Name: cvpy
Version: 0.0.0
Summary: Computer Vision in python.
Home-page: UNKNOWN
Author: ZQPei
Author-email: peiziqiang@gmail.com
License: MIT
Platform: all
